odoo_selenium/__init__.py
odoo_selenium/expectations.py
odoo_selenium/selenium.py
odoo_selenium-0.1.6.dist-info/LICENSE
odoo_selenium-0.1.6.dist-info/WHEEL
odoo_selenium-0.1.6.dist-info/METADATA
odoo_selenium-0.1.6.dist-info/RECORD
