Metadata-Version: 2.1
Name: odoo-selenium
Version: 0.1.6
Summary: Utilities that make it easy to quickly write and develop Odoo tests using Selenium.
Author-email: Vauxoo <info@vauxoo.com>
Requires-Python: >=3.7.0
Classifier: Intended Audience :: Developers
Classifier: Topic :: Software Development :: Testing
Classifier: Topic :: Software Development :: Libraries :: Python Modules
Classifier: Operating System :: Unix
Classifier: Operating System :: POSIX
Classifier: Operating System :: Microsoft :: Windows
Classifier: Operating System :: MacOS
Classifier: Programming Language :: Python :: 3
Classifier: Programming Language :: Python :: 3.7
Classifier: Programming Language :: Python :: 3.8
Classifier: Programming Language :: Python :: 3.9
Classifier: Programming Language :: Python :: 3.10
Classifier: Programming Language :: Python :: 3.11
Requires-Dist: selenium >= 4.11
Project-URL: Source, https://github.com/vauxoo/odoo-selenium
